Workbook

Sheet Invoice
F2: TAX INVOICE
B5: Tax invoice
B7: INVOICE NO. | D7: ISSUED | E7: DUE | F7: AMOUNT DUE (AUD)
B8: [INV-0001] | D8: 46304 | E8: =D8+14 | F8: =F27
B10: BILL TO | D10: FROM
B11: [Client company name] | D11: Obsydian Technologies Pty Ltd
B12: [Attention: contact name] | D12: ABN 70 682 110 363
B13: [Street address, City STATE Postcode] | D13: [Street address]
B14: [ABN, if they have one] | D14: hello@obsydiantechnologies.com
B16: DESCRIPTION | C16: QTY | D16: RATE | E16: GST | F16: AMOUNT
B17: Discovery and architecture | C17: 1 | D17: 18500 | E17: =IF(C17*D17=0,"",ROUND(C17*D17*0.1,2)) | F17: =IF(C17*D17=0,"",C17*D17)
B18: Platform build: sprint 1 to 3 | C18: 3 | D18: 24000 | E18: =IF(C18*D18=0,"",ROUND(C18*D18*0.1,2)) | F18: =IF(C18*D18=0,"",C18*D18)
B19: Cloud environment, monthly | C19: 1 | D19: 3200 | E19: =IF(C19*D19=0,"",ROUND(C19*D19*0.1,2)) | F19: =IF(C19*D19=0,"",C19*D19)
E20: =IF(C20*D20=0,"",ROUND(C20*D20*0.1,2)) | F20: =IF(C20*D20=0,"",C20*D20)
E21: =IF(C21*D21=0,"",ROUND(C21*D21*0.1,2)) | F21: =IF(C21*D21=0,"",C21*D21)
E22: =IF(C22*D22=0,"",ROUND(C22*D22*0.1,2)) | F22: =IF(C22*D22=0,"",C22*D22)
E23: =IF(C23*D23=0,"",ROUND(C23*D23*0.1,2)) | F23: =IF(C23*D23=0,"",C23*D23)
E24: =IF(C24*D24=0,"",ROUND(C24*D24*0.1,2)) | F24: =IF(C24*D24=0,"",C24*D24)
D25: Subtotal | F25: =SUM(F17:F24)
D26: GST 10% | F26: =SUM(E17:E24)
D27: TOTAL AUD | F27: =F25+F26
B30: HOW TO PAY
B31: ACCOUNT NAME | C31: BSB | E31: ACCOUNT | F31: REFERENCE
B32: Obsydian Technologies Pty Ltd | C32: [000-000] | E32: [0000 0000] | F32: =B8
B34: Payment is due within 14 days. Please use the invoice number as your reference.

Sheet Receipt
F2: RECEIPT
B5: Receipt
B6: Payment received. Thank you.
B8: RECEIPT NO. | D8: PAID ON | E8: FOR INVOICE | F8: METHOD
B9: [REC-0001] | D9: 46315 | E9: =Invoice!B8 | F9: [Bank transfer]
B11: RECEIVED FROM | D11: RECEIVED BY
B12: =Invoice!B11 | D12: Obsydian Technologies Pty Ltd
B13: =Invoice!B12 | D13: ABN 70 682 110 363
B15: DESCRIPTION | E15: GST | F15: AMOUNT
B16: ="Payment against invoice "&Invoice!B8 | E16: =Invoice!F26 | F16: =Invoice!F27
D18: Includes GST | F18: =E16
D19: Balance remaining | F19: =Invoice!F27-F16
D20: PAID AUD | F20: =F16
B23: Keep this receipt for your records. Issued by Obsydian Technologies Pty Ltd, ABN 70 682 110 363.

Sheet How to use
B2: How to use this workbook
B4: 01 Fill the bracketed cells on the Invoice sheet: invoice number, client details and bank details.
B5: 02 Type up to eight line items: a description, a quantity and a rate. GST, amounts and totals calculate themselves.
B6: 03 The due date is 14 days after the issue date (D8). Change the formula in E8 if the terms differ.
B7: 04 When the client pays, fill the receipt number, date and method on the Receipt sheet. Everything else follows the invoice.
B8: 05 To send: File, Export (or Save as), PDF. Send the PDF, never the workbook.
B9: 06 Install General Sans first (free from fontshare.com) so the type matches the brand.
B10: 07 Rates include no GST. If Obsydian is not registered for GST on this work, set the 0.1 in column E to 0 and call it an invoice, not a tax invoice.
